{"yemekler":[
  { 
	"yemek_id":1, 
   	"yemek_adi":"ÇORBA" ,
	"yemek_aciklama":"Tarifin Detayları " ,
	"yemek_tur":"çorbalar" ,
	"yemek_pisirme_suresi":"20" ,
	"yemek_kisi_sayisi":"10" ,
	"yemek_resim":"Doe" ,
	"yemek_malezemeler":"Salça" 
 },
 { 
	"yemek_id":2, 
   	"yemek_adi":"Ispanak" ,
	"yemek_aciklama":"Doe" ,
	"yemek_tur":"Ana Yemek" ,
	"yemek_pisirme_suresi":"35" ,
	"yemek_kisi_sayisi":"5" ,
	"yemek_resim":"Doe" ,
	"yemek_malezemeler":"Salça" 
 },
 { 
	"yemek_id":3, 
   	"yemek_adi":"Sütlaç" ,
	"yemek_aciklama":"Doe" ,
	"yemek_tur":"Doe" ,
	"yemek_pisirme_suresi":"60" ,
	"yemek_kisi_sayisi":"20" ,
	"yemek_resim":"Doe" ,
	"yemek_malezemeler":"Salça" 
 },
 { 
	"yemek_id":4, 
   	"yemek_adi":"Pırasa" ,
	"yemek_aciklama":"Doe" ,
	"yemek_tur":"Doe" ,
	"yemek_pisirme_suresi":"40" ,
	"yemek_kisi_sayisi":"10" ,
	"yemek_resim":"Doe" ,
	"yemek_malezemeler":"Salça" 
 }
]}